{"stats":{"minecraft:mined":{"minecraft:large_fern":1},"minecraft:custom":{"minecraft:open_barrel":1,"minecraft:fill_cauldron":1,"minecraft:leave_game":24,"minecraft:time_since_death":857878,"minecraft:climb_one_cm":21006,"minecraft:sprint_one_cm":712536,"minecraft:walk_one_cm":1306283,"minecraft:drop":8,"minecraft:play_time":857878,"minecraft:sneak_time":57368,"minecraft:walk_under_water_one_cm":7678,"minecraft:jump":9096,"minecraft:walk_on_water_one_cm":33545,"minecraft:total_world_time":1295280,"minecraft:pot_flower":2,"minecraft:time_since_rest":857878,"minecraft:damage_taken":320,"minecraft:trigger_trapped_chest":17,"minecraft:swim_one_cm":15709,"minecraft:fly_one_cm":6607239,"minecraft:open_chest":74,"minecraft:crouch_one_cm":78097,"minecraft:fall_one_cm":12534,"minecraft:inspect_dispenser":32},"minecraft:dropped":{"minecraft:ghast_spawn_egg":4,"minecraft:dispenser":1,"minecraft:sunflower":1,"minecraft:iron_pickaxe":1,"minecraft:mycelium":1},"minecraft:used":{"minecraft:orange_dye":1,"minecraft:petrified_oak_slab":12,"minecraft:enchanting_table":1,"minecraft:iron_bars":13,"minecraft:acacia_log":1,"minecraft:flint_and_steel":6,"minecraft:melon":8,"minecraft:armor_stand":1,"minecraft:redstone":38,"minecraft:dispenser":8,"minecraft:polished_blackstone":1,"minecraft:ladder":24,"minecraft:oak_sign":4,"minecraft:mycelium":361,"minecraft:chest":4,"minecraft:tinted_glass":7,"minecraft:white_terracotta":485,"minecraft:ender_chest":2,"minecraft:stone":872,"minecraft:quartz_stairs":19,"minecraft:grass":16,"minecraft:green_terracotta":159,"minecraft:netherrack":3,"minecraft:orange_bed":9,"minecraft:brewing_stand":2,"minecraft:dirt":2,"minecraft:ancient_debris":29,"minecraft:anvil":1,"minecraft:hopper":1,"minecraft:jungle_planks":10,"minecraft:cobblestone_wall":12,"minecraft:jungle_slab":12,"minecraft:orange_wool":6,"minecraft:oak_wood":78,"minecraft:pink_terracotta":160,"minecraft:spruce_fence":1,"minecraft:cyan_wool":162,"minecraft:granite":15,"minecraft:azure_bluet":3,"minecraft:fern":8,"minecraft:polished_blackstone_slab":9,"minecraft:brown_terracotta":82,"minecraft:glass":8,"minecraft:waxed_oxidized_copper":4,"minecraft:stone_brick_slab":26,"minecraft:dark_oak_planks":35,"minecraft:packed_ice":16,"minecraft:lava_bucket":10,"minecraft:netherite_shovel":1,"minecraft:bookshelf":6,"minecraft:quartz_pillar":147,"minecraft:quartz_slab":12,"minecraft:waxed_cut_copper":9,"minecraft:black_stained_glass_pane":1,"minecraft:lantern":7,"minecraft:grass_block":104,"minecraft:brick_stairs":32,"minecraft:smooth_sandstone":12,"minecraft:acacia_slab":66,"minecraft:dark_oak_slab":21,"minecraft:barrel":17,"minecraft:stone_brick_stairs":33,"minecraft:stone_bricks":670,"minecraft:light_gray_wool":53,"minecraft:tripwire_hook":4,"minecraft:birch_trapdoor":619,"minecraft:lime_concrete":30,"minecraft:repeater":22,"minecraft:redstone_lamp":5,"minecraft:magma_block":7,"minecraft:bow":15,"minecraft:tall_grass":11,"minecraft:furnace":3,"minecraft:podzol":92,"minecraft:acacia_fence":68,"minecraft:gold_block":5,"minecraft:trapped_chest":1,"minecraft:stone_pressure_plate":7,"minecraft:cooked_beef":2,"minecraft:acacia_planks":408,"minecraft:large_fern":7,"minecraft:dark_oak_stairs":29,"minecraft:water_bucket":151,"minecraft:cobblestone_stairs":110,"minecraft:spruce_door":3,"minecraft:cut_copper_slab":1,"minecraft:acacia_trapdoor":815,"minecraft:polished_andesite":2,"minecraft:jungle_fence":44,"minecraft:oak_planks":383,"minecraft:blue_wool":1,"minecraft:waxed_oxidized_cut_copper":2,"minecraft:cauldron":1,"minecraft:spruce_sign":25,"minecraft:clay":5,"minecraft:glow_ink_sac":1,"minecraft:cobblestone_slab":21,"minecraft:oak_leaves":365,"minecraft:pink_concrete":21,"minecraft:white_wool":11,"minecraft:glow_item_frame":5,"minecraft:waxed_exposed_copper":3,"minecraft:lime_terracotta":56,"minecraft:sand":6,"minecraft:rail":4,"minecraft:terracotta":25,"minecraft:vine":13,"minecraft:light_blue_concrete":45,"minecraft:oak_slab":68,"minecraft:tnt":3,"minecraft:crafting_table":1,"minecraft:crimson_trapdoor":472,"minecraft:smooth_red_sandstone":39,"minecraft:blast_furnace":2,"minecraft:light_gray_terracotta":4,"minecraft:acacia_leaves":195,"minecraft:campfire":52,"minecraft:chiseled_quartz_block":12,"minecraft:painting":246,"minecraft:spruce_log":151,"minecraft:birch_fence":55,"minecraft:redstone_torch":13,"minecraft:oak_log":507,"minecraft:black_terracotta":65,"minecraft:gray_terracotta":68,"minecraft:flower_pot":2,"minecraft:light":268,"minecraft:acacia_stairs":49,"minecraft:warped_trapdoor":904,"minecraft:ghast_spawn_egg":187,"minecraft:oxeye_daisy":3,"minecraft:birch_fence_gate":6,"minecraft:dark_oak_log":23,"minecraft:birch_slab":40,"minecraft:cracked_polished_blackstone_bricks":32,"minecraft:deepslate_iron_ore":58,"minecraft:string":3,"minecraft:barrier":1700,"minecraft:cyan_carpet":26,"minecraft:netherite_axe":1,"minecraft:jungle_stairs":12,"minecraft:magenta_concrete":5,"minecraft:stone_slab":65,"minecraft:spruce_trapdoor":23,"minecraft:oak_pressure_plate":1,"minecraft:chiseled_stone_bricks":10,"minecraft:fishing_rod":2,"minecraft:cobblestone":698,"minecraft:azalea_leaves":5,"minecraft:dark_oak_fence":1,"minecraft:lapis_block":1,"minecraft:chain":1,"minecraft:glass_pane":102,"minecraft:dandelion":14,"minecraft:candle":12,"minecraft:cobweb":12,"minecraft:birch_stairs":3},"minecraft:picked_up":{"minecraft:fishing_rod":34,"minecraft:ghast_spawn_egg":4,"minecraft:mycelium":1,"minecraft:redstone_torch":1,"minecraft:poppy":2,"minecraft:iron_pickaxe":1,"minecraft:redstone":2,"minecraft:rail":2,"minecraft:repeater":1,"minecraft:tripwire_hook":2,"minecraft:lantern":1,"minecraft:stone_bricks":96,"minecraft:dandelion":4,"minecraft:dispenser":1,"minecraft:painting":1,"minecraft:spruce_sign":4}},"DataVersion":2975}